composite_silhouette/__init__.py
composite_silhouette/composite_silhouette.py
composite_silhouette-0.1.2.dist-info/licenses/LICENSE
composite_silhouette-0.1.2.dist-info/METADATA
composite_silhouette-0.1.2.dist-info/WHEEL
composite_silhouette-0.1.2.dist-info/top_level.txt
composite_silhouette-0.1.2.dist-info/RECORD
